[{"time": 1739679600, "countries": [{"name": "Bulgaria", "value": 2}, {"name": "India", "value": 1}, {"name": "Australia", "value": 3}]}, {"time": 1739687700, "countries": [{"name": "India", "value": 1}, {"name": "Bulgaria", "value": 2}, {"name": "Australia", "value": 3}]}, {"time": 1739692500, "countries": [{"name": "Bulgaria", "value": 2}, {"name": "Australia", "value": 3}, {"name": "India", "value": 1}]}, {"time": 1739697000, "countries": [{"name": "India", "value": 1}, {"name": "Australia", "value": 3}, {"name": "Bulgaria", "value": 2}]}, {"time": 1739689800, "countries": [{"name": "Australia", "value": 3}, {"name": "India", "value": 1}, {"name": "Bulgaria", "value": 2}]}, {"time": 1739687100, "countries": [{"name": "Bulgaria", "value": 2}, {"name": "India", "value": 1}, {"name": "Australia", "value": 3}]}, {"time": 1739681700, "countries": [{"name": "India", "value": 1}, {"name": "Bulgaria", "value": 2}, {"name": "Australia", "value": 3}]}, {"time": 1739695500, "countries": [{"name": "India", "value": 1}, {"name": "Australia", "value": 3}, {"name": "Bulgaria", "value": 2}]}, {"time": 1739685600, "countries": [{"name": "Australia", "value": 3}, {"name": "India", "value": 1}, {"name": "Bulgaria", "value": 2}]}, {"time": 1739684700, "countries": [{"name": "Australia", "value": 3}, {"name": "India", "value": 1}, {"name": "Bulgaria", "value": 2}]}, {"time": 1739685300, "countries": [{"name": "Bulgaria", "value": 2}, {"name": "Australia", "value": 3}, {"name": "India", "value": 1}]}, {"time": 1739684100, "countries": [{"name": "Bulgaria", "value": 2}, {"name": "Australia", "value": 3}, {"name": "India", "value": 1}]}, {"time": 1739690400, "countries": [{"name": "Australia", "value": 3}, {"name": "Bulgaria", "value": 2}, {"name": "India", "value": 1}]}, {"time": 1739696100, "countries": [{"name": "Bulgaria", "value": 2}, {"name": "India", "value": 1}, {"name": "Australia", "value": 3}]}, {"time": 1739699700, "countries": [{"name": "Australia", "value": 3}, {"name": "India", "value": 1}, {"name": "Bulgaria", "value": 2}]}, {"time": 1739691900, "countries": [{"name": "Bulgaria", "value": 2}, {"name": "India", "value": 1}, {"name": "Australia", "value": 3}]}, {"time": 1739691300, "countries": [{"name": "Australia", "value": 3}, {"name": "India", "value": 1}, {"name": "Bulgaria", "value": 2}]}, {"time": 1739689200, "countries": [{"name": "India", "value": 1}, {"name": "Australia", "value": 3}, {"name": "Bulgaria", "value": 2}]}, {"time": 1739694600, "countries": [{"name": "Bulgaria", "value": 2}, {"name": "India", "value": 1}, {"name": "Australia", "value": 3}]}, {"time": 1739683800, "countries": [{"name": "India", "value": 1}, {"name": "Bulgaria", "value": 2}, {"name": "Australia", "value": 3}]}, {"time": 1739696400, "countries": [{"name": "India", "value": 1}, {"name": "Australia", "value": 3}, {"name": "Bulgaria", "value": 2}]}, {"time": 1739681400, "countries": [{"name": "Australia", "value": 3}, {"name": "India", "value": 1}, {"name": "Bulgaria", "value": 2}]}, {"time": 1739693700, "countries": [{"name": "India", "value": 1}, {"name": "Australia", "value": 3}, {"name": "Bulgaria", "value": 2}]}, {"time": 1739694900, "countries": [{"name": "Australia", "value": 3}, {"name": "India", "value": 1}, {"name": "Bulgaria", "value": 2}]}, {"time": 1739696700, "countries": [{"name": "Bulgaria", "value": 2}, {"name": "India", "value": 1}, {"name": "Australia", "value": 3}]}, {"time": 1739694300, "countries": [{"name": "India", "value": 1}, {"name": "Bulgaria", "value": 2}, {"name": "Australia", "value": 3}]}, {"time": 1739688900, "countries": [{"name": "India", "value": 1}, {"name": "Bulgaria", "value": 2}, {"name": "Australia", "value": 3}]}, {"time": 1739682000, "countries": [{"name": "Bulgaria", "value": 2}, {"name": "India", "value": 1}, {"name": "Australia", "value": 3}]}, {"time": 1739694000, "countries": [{"name": "Bulgaria", "value": 2}, {"name": "Australia", "value": 3}, {"name": "India", "value": 1}]}, {"time": 1739685000, "countries": [{"name": "India", "value": 1}, {"name": "Australia", "value": 3}, {"name": "Bulgaria", "value": 2}]}, {"time": 1739688600, "countries": [{"name": "Bulgaria", "value": 2}, {"name": "Australia", "value": 3}, {"name": "India", "value": 1}]}, {"time": 1739699400, "countries": [{"name": "Bulgaria", "value": 2}, {"name": "Australia", "value": 3}, {"name": "India", "value": 1}]}, {"time": 1739687400, "countries": [{"name": "Bulgaria", "value": 2}, {"name": "Australia", "value": 3}, {"name": "India", "value": 1}]}, {"time": 1739679300, "countries": [{"name": "India", "value": 1}, {"name": "Bulgaria", "value": 2}, {"name": "Australia", "value": 3}]}, {"time": 1739684400, "countries": [{"name": "India", "value": 1}, {"name": "Australia", "value": 3}, {"name": "Bulgaria", "value": 2}]}, {"time": 1739678400, "countries": [{"name": "Bulgaria", "value": 2}, {"name": "India", "value": 1}, {"name": "Australia", "value": 3}]}, {"time": 1739690100, "countries": [{"name": "Bulgaria", "value": 2}, {"name": "Australia", "value": 3}, {"name": "India", "value": 1}]}, {"time": 1739695200, "countries": [{"name": "Australia", "value": 3}, {"name": "Bulgaria", "value": 2}, {"name": "India", "value": 1}]}, {"time": 1739686200, "countries": [{"name": "Bulgaria", "value": 2}, {"name": "India", "value": 1}, {"name": "Australia", "value": 3}]}, {"time": 1739682600, "countries": [{"name": "Bulgaria", "value": 2}, {"name": "Australia", "value": 3}, {"name": "India", "value": 1}]}, {"time": 1739682900, "countries": [{"name": "Bulgaria", "value": 2}, {"name": "India", "value": 1}, {"name": "Australia", "value": 3}]}, {"time": 1739692200, "countries": [{"name": "India", "value": 1}, {"name": "Australia", "value": 3}, {"name": "Bulgaria", "value": 2}]}, {"time": 1739692800, "countries": [{"name": "India", "value": 1}, {"name": "Australia", "value": 3}, {"name": "Bulgaria", "value": 2}]}, {"time": 1739690700, "countries": [{"name": "Australia", "value": 3}, {"name": "India", "value": 1}, {"name": "Bulgaria", "value": 2}]}, {"time": 1739697900, "countries": [{"name": "India", "value": 1}, {"name": "Bulgaria", "value": 2}, {"name": "Australia", "value": 3}]}, {"time": 1739679000, "countries": [{"name": "India", "value": 1}, {"name": "Australia", "value": 3}, {"name": "Bulgaria", "value": 2}]}, {"time": 1739679900, "countries": [{"name": "Australia", "value": 3}, {"name": "India", "value": 1}, {"name": "Bulgaria", "value": 2}]}, {"time": 1739698500, "countries": [{"name": "Australia", "value": 3}, {"name": "India", "value": 1}, {"name": "Bulgaria", "value": 2}]}, {"time": 1739680200, "countries": [{"name": "Bulgaria", "value": 2}, {"name": "Australia", "value": 3}, {"name": "India", "value": 1}]}, {"time": 1739689500, "countries": [{"name": "India", "value": 1}, {"name": "Bulgaria", "value": 2}, {"name": "Australia", "value": 3}]}, {"time": 1739699100, "countries": [{"name": "India", "value": 1}, {"name": "Australia", "value": 3}, {"name": "Bulgaria", "value": 2}]}, {"time": 1739698800, "countries": [{"name": "Australia", "value": 3}, {"name": "Bulgaria", "value": 2}, {"name": "India", "value": 1}]}, {"time": 1739688000, "countries": [{"name": "Bulgaria", "value": 2}, {"name": "India", "value": 1}, {"name": "Australia", "value": 3}]}, {"time": 1739691000, "countries": [{"name": "Australia", "value": 3}, {"name": "Bulgaria", "value": 2}, {"name": "India", "value": 1}]}, {"time": 1739698200, "countries": [{"name": "India", "value": 1}, {"name": "Bulgaria", "value": 2}, {"name": "Australia", "value": 3}]}, {"time": 1739686800, "countries": [{"name": "Australia", "value": 3}, {"name": "Bulgaria", "value": 2}, {"name": "India", "value": 1}]}, {"time": 1739693100, "countries": [{"name": "Bulgaria", "value": 2}, {"name": "India", "value": 1}, {"name": "Australia", "value": 3}]}, {"time": 1739681100, "countries": [{"name": "India", "value": 1}, {"name": "Bulgaria", "value": 2}, {"name": "Australia", "value": 3}]}, {"time": 1739688300, "countries": [{"name": "Australia", "value": 3}, {"name": "Bulgaria", "value": 2}, {"name": "India", "value": 1}]}, {"time": 1739685900, "countries": [{"name": "Australia", "value": 3}, {"name": "India", "value": 1}, {"name": "Bulgaria", "value": 2}]}, {"time": 1739700000, "countries": [{"name": "Bulgaria", "value": 2}, {"name": "India", "value": 1}, {"name": "Australia", "value": 3}]}, {"time": 1739695800, "countries": [{"name": "India", "value": 1}, {"name": "Australia", "value": 3}, {"name": "Bulgaria", "value": 2}]}, {"time": 1739680800, "countries": [{"name": "India", "value": 1}, {"name": "Australia", "value": 3}, {"name": "Bulgaria", "value": 2}]}, {"time": 1739682300, "countries": [{"name": "Bulgaria", "value": 2}, {"name": "India", "value": 1}, {"name": "Australia", "value": 3}]}, {"time": 1739697600, "countries": [{"name": "India", "value": 1}, {"name": "Australia", "value": 3}, {"name": "Bulgaria", "value": 2}]}, {"time": 1739691600, "countries": [{"name": "Bulgaria", "value": 2}, {"name": "India", "value": 1}, {"name": "Australia", "value": 3}]}, {"time": 1739697300, "countries": [{"name": "India", "value": 1}, {"name": "Bulgaria", "value": 2}, {"name": "Australia", "value": 3}]}, {"time": 1739683200, "countries": [{"name": "Australia", "value": 3}, {"name": "India", "value": 1}, {"name": "Bulgaria", "value": 2}]}, {"time": 1739680500, "countries": [{"name": "India", "value": 1}, {"name": "Australia", "value": 3}, {"name": "Bulgaria", "value": 2}]}, {"time": 1739678700, "countries": [{"name": "Australia", "value": 3}, {"name": "India", "value": 1}, {"name": "Bulgaria", "value": 2}]}, {"time": 1739683500, "countries": [{"name": "Australia", "value": 3}, {"name": "India", "value": 1}, {"name": "Bulgaria", "value": 2}]}, {"time": 1739686500, "countries": [{"name": "Australia", "value": 3}, {"name": "India", "value": 1}, {"name": "Bulgaria", "value": 2}]}, {"time": 1739693400, "countries": [{"name": "Australia", "value": 3}, {"name": "India", "value": 1}, {"name": "Bulgaria", "value": 2}]}]