[{"time": 1737903600, "users": [{"name": "impulsecanopener30", "nodes": 2}, {"name": "gloomyred82", "nodes": 1}, {"name": "simplefrog47", "nodes": 1}]}, {"time": 1737914400, "users": [{"name": "simplefrog47", "nodes": 1}, {"name": "impulsecanopener30", "nodes": 2}, {"name": "gloomyred82", "nodes": 1}]}, {"time": 1737867600, "users": [{"name": "gloomyred82", "nodes": 1}, {"name": "impulsecanopener30", "nodes": 2}, {"name": "simplefrog47", "nodes": 1}]}, {"time": 1737878400, "users": [{"name": "gloomyred82", "nodes": 1}, {"name": "simplefrog47", "nodes": 1}, {"name": "impulsecanopener30", "nodes": 2}]}, {"time": 1737943200, "users": [{"name": "gloomyred82", "nodes": 1}, {"name": "impulsecanopener30", "nodes": 2}, {"name": "simplefrog47", "nodes": 1}]}, {"time": 1737896400, "users": [{"name": "gloomyred82", "nodes": 1}, {"name": "impulsecanopener30", "nodes": 2}, {"name": "simplefrog47", "nodes": 1}]}, {"time": 1737936000, "users": [{"name": "impulsecanopener30", "nodes": 2}, {"name": "simplefrog47", "nodes": 1}, {"name": "gloomyred82", "nodes": 1}]}, {"time": 1737939600, "users": [{"name": "gloomyred82", "nodes": 1}, {"name": "impulsecanopener30", "nodes": 2}, {"name": "simplefrog47", "nodes": 1}]}, {"time": 1737885600, "users": [{"name": "simplefrog47", "nodes": 1}, {"name": "gloomyred82", "nodes": 1}, {"name": "impulsecanopener30", "nodes": 2}]}, {"time": 1737871200, "users": [{"name": "impulsecanopener30", "nodes": 2}, {"name": "simplefrog47", "nodes": 1}, {"name": "gloomyred82", "nodes": 1}]}, {"time": 1737889200, "users": [{"name": "impulsecanopener30", "nodes": 2}, {"name": "gloomyred82", "nodes": 1}, {"name": "simplefrog47", "nodes": 1}]}, {"time": 1737928800, "users": [{"name": "gloomyred82", "nodes": 1}, {"name": "simplefrog47", "nodes": 1}, {"name": "impulsecanopener30", "nodes": 2}]}, {"time": 1737921600, "users": [{"name": "simplefrog47", "nodes": 1}, {"name": "gloomyred82", "nodes": 1}, {"name": "impulsecanopener30", "nodes": 2}]}, {"time": 1737910800, "users": [{"name": "impulsecanopener30", "nodes": 2}, {"name": "gloomyred82", "nodes": 1}, {"name": "simplefrog47", "nodes": 1}]}, {"time": 1737882000, "users": [{"name": "impulsecanopener30", "nodes": 2}, {"name": "gloomyred82", "nodes": 1}, {"name": "simplefrog47", "nodes": 1}]}, {"time": 1737907200, "users": [{"name": "simplefrog47", "nodes": 1}, {"name": "impulsecanopener30", "nodes": 2}, {"name": "gloomyred82", "nodes": 1}]}, {"time": 1737932400, "users": [{"name": "simplefrog47", "nodes": 1}, {"name": "gloomyred82", "nodes": 1}, {"name": "impulsecanopener30", "nodes": 2}]}, {"time": 1737946800, "users": [{"name": "gloomyred82", "nodes": 1}, {"name": "impulsecanopener30", "nodes": 2}, {"name": "simplefrog47", "nodes": 1}]}, {"time": 1737864000, "users": [{"name": "simplefrog47", "nodes": 1}, {"name": "gloomyred82", "nodes": 1}, {"name": "impulsecanopener30", "nodes": 2}]}, {"time": 1737925200, "users": [{"name": "gloomyred82", "nodes": 1}, {"name": "impulsecanopener30", "nodes": 2}, {"name": "simplefrog47", "nodes": 1}]}, {"time": 1737900000, "users": [{"name": "simplefrog47", "nodes": 1}, {"name": "impulsecanopener30", "nodes": 3}, {"name": "gloomyred82", "nodes": 1}]}, {"time": 1737892800, "users": [{"name": "impulsecanopener30", "nodes": 2}, {"name": "gloomyred82", "nodes": 1}, {"name": "simplefrog47", "nodes": 1}]}, {"time": 1737918000, "users": [{"name": "simplefrog47", "nodes": 1}, {"name": "impulsecanopener30", "nodes": 2}, {"name": "gloomyred82", "nodes": 1}]}, {"time": 1737860400, "users": [{"name": "impulsecanopener30", "nodes": 2}, {"name": "gloomyred82", "nodes": 1}, {"name": "simplefrog47", "nodes": 1}]}, {"time": 1737874800, "users": [{"name": "simplefrog47", "nodes": 1}, {"name": "gloomyred82", "nodes": 1}, {"name": "impulsecanopener30", "nodes": 2}]}]