[{"time": 1737553500, "users": [{"name": "impulsecanopener30", "nodes": 2}, {"name": "gloomyred82", "nodes": 1}, {"name": "simplefrog47", "nodes": 1}]}, {"time": 1737545700, "users": [{"name": "impulsecanopener30", "nodes": 2}, {"name": "simplefrog47", "nodes": 1}, {"name": "gloomyred82", "nodes": 1}]}, {"time": 1737546900, "users": [{"name": "impulsecanopener30", "nodes": 2}, {"name": "gloomyred82", "nodes": 1}, {"name": "simplefrog47", "nodes": 1}]}, {"time": 1737561900, "users": [{"name": "impulsecanopener30", "nodes": 2}, {"name": "simplefrog47", "nodes": 1}, {"name": "gloomyred82", "nodes": 1}]}, {"time": 1737560100, "users": [{"name": "impulsecanopener30", "nodes": 2}, {"name": "gloomyred82", "nodes": 1}, {"name": "simplefrog47", "nodes": 1}]}, {"time": 1737551700, "users": [{"name": "impulsecanopener30", "nodes": 2}, {"name": "simplefrog47", "nodes": 1}, {"name": "gloomyred82", "nodes": 1}]}, {"time": 1737554400, "users": [{"name": "gloomyred82", "nodes": 1}, {"name": "impulsecanopener30", "nodes": 2}, {"name": "simplefrog47", "nodes": 1}]}, {"time": 1737553800, "users": [{"name": "simplefrog47", "nodes": 1}, {"name": "gloomyred82", "nodes": 1}, {"name": "impulsecanopener30", "nodes": 2}]}, {"time": 1737554700, "users": [{"name": "impulsecanopener30", "nodes": 2}, {"name": "gloomyred82", "nodes": 1}, {"name": "simplefrog47", "nodes": 1}]}, {"time": 1737552600, "users": [{"name": "simplefrog47", "nodes": 1}, {"name": "impulsecanopener30", "nodes": 2}, {"name": "gloomyred82", "nodes": 1}]}, {"time": 1737558000, "users": [{"name": "impulsecanopener30", "nodes": 2}, {"name": "gloomyred82", "nodes": 1}, {"name": "simplefrog47", "nodes": 1}]}, {"time": 1737556200, "users": [{"name": "simplefrog47", "nodes": 1}, {"name": "gloomyred82", "nodes": 1}, {"name": "impulsecanopener30", "nodes": 2}]}, {"time": 1737548100, "users": [{"name": "impulsecanopener30", "nodes": 2}, {"name": "gloomyred82", "nodes": 1}, {"name": "simplefrog47", "nodes": 1}]}, {"time": 1737546300, "users": [{"name": "impulsecanopener30", "nodes": 2}, {"name": "simplefrog47", "nodes": 1}, {"name": "gloomyred82", "nodes": 1}]}, {"time": 1737553200, "users": [{"name": "simplefrog47", "nodes": 1}, {"name": "impulsecanopener30", "nodes": 2}, {"name": "gloomyred82", "nodes": 1}]}, {"time": 1737558600, "users": [{"name": "simplefrog47", "nodes": 1}, {"name": "gloomyred82", "nodes": 1}, {"name": "impulsecanopener30", "nodes": 2}]}, {"time": 1737555000, "users": [{"name": "simplefrog47", "nodes": 1}, {"name": "impulsecanopener30", "nodes": 2}, {"name": "gloomyred82", "nodes": 1}]}, {"time": 1737554100, "users": [{"name": "gloomyred82", "nodes": 1}, {"name": "simplefrog47", "nodes": 1}, {"name": "impulsecanopener30", "nodes": 2}]}, {"time": 1737557700, "users": [{"name": "impulsecanopener30", "nodes": 2}, {"name": "gloomyred82", "nodes": 1}, {"name": "simplefrog47", "nodes": 1}]}, {"time": 1737550800, "users": [{"name": "simplefrog47", "nodes": 1}, {"name": "gloomyred82", "nodes": 1}, {"name": "impulsecanopener30", "nodes": 2}]}, {"time": 1737549300, "users": [{"name": "simplefrog47", "nodes": 1}, {"name": "impulsecanopener30", "nodes": 2}, {"name": "gloomyred82", "nodes": 1}]}, {"time": 1737557400, "users": [{"name": "simplefrog47", "nodes": 1}, {"name": "impulsecanopener30", "nodes": 2}, {"name": "gloomyred82", "nodes": 1}]}, {"time": 1737555600, "users": [{"name": "simplefrog47", "nodes": 1}, {"name": "impulsecanopener30", "nodes": 2}, {"name": "gloomyred82", "nodes": 1}]}, {"time": 1737549000, "users": [{"name": "simplefrog47", "nodes": 1}, {"name": "gloomyred82", "nodes": 1}, {"name": "impulsecanopener30", "nodes": 2}]}, {"time": 1737550500, "users": [{"name": "impulsecanopener30", "nodes": 2}, {"name": "gloomyred82", "nodes": 1}, {"name": "simplefrog47", "nodes": 1}]}, {"time": 1737547500, "users": [{"name": "simplefrog47", "nodes": 1}, {"name": "gloomyred82", "nodes": 1}, {"name": "impulsecanopener30", "nodes": 2}]}, {"time": 1737561000, "users": [{"name": "gloomyred82", "nodes": 1}, {"name": "impulsecanopener30", "nodes": 2}, {"name": "simplefrog47", "nodes": 1}]}, {"time": 1737552900, "users": [{"name": "simplefrog47", "nodes": 1}, {"name": "impulsecanopener30", "nodes": 2}, {"name": "gloomyred82", "nodes": 1}]}, {"time": 1737548700, "users": [{"name": "simplefrog47", "nodes": 1}, {"name": "gloomyred82", "nodes": 1}, {"name": "impulsecanopener30", "nodes": 2}]}, {"time": 1737547200, "users": [{"name": "simplefrog47", "nodes": 1}, {"name": "gloomyred82", "nodes": 1}, {"name": "impulsecanopener30", "nodes": 2}]}, {"time": 1737544500, "users": [{"name": "impulsecanopener30", "nodes": 2}, {"name": "gloomyred82", "nodes": 1}, {"name": "simplefrog47", "nodes": 1}]}, {"time": 1737547800, "users": [{"name": "simplefrog47", "nodes": 1}, {"name": "impulsecanopener30", "nodes": 2}, {"name": "gloomyred82", "nodes": 1}]}, {"time": 1737543300, "users": [{"name": "gloomyred82", "nodes": 1}, {"name": "impulsecanopener30", "nodes": 2}, {"name": "simplefrog47", "nodes": 1}]}, {"time": 1737542100, "users": [{"name": "gloomyred82", "nodes": 1}, {"name": "impulsecanopener30", "nodes": 2}, {"name": "simplefrog47", "nodes": 1}]}, {"time": 1737561600, "users": [{"name": "simplefrog47", "nodes": 1}, {"name": "gloomyred82", "nodes": 1}, {"name": "impulsecanopener30", "nodes": 2}]}, {"time": 1737555900, "users": [{"name": "simplefrog47", "nodes": 1}, {"name": "impulsecanopener30", "nodes": 2}, {"name": "gloomyred82", "nodes": 1}]}, {"time": 1737550200, "users": [{"name": "simplefrog47", "nodes": 1}, {"name": "impulsecanopener30", "nodes": 2}, {"name": "gloomyred82", "nodes": 1}]}, {"time": 1737542700, "users": [{"name": "impulsecanopener30", "nodes": 2}, {"name": "gloomyred82", "nodes": 1}, {"name": "simplefrog47", "nodes": 1}]}, {"time": 1737562200, "users": [{"name": "simplefrog47", "nodes": 1}, {"name": "impulsecanopener30", "nodes": 2}, {"name": "gloomyred82", "nodes": 1}]}, {"time": 1737544800, "users": [{"name": "impulsecanopener30", "nodes": 2}, {"name": "simplefrog47", "nodes": 1}, {"name": "gloomyred82", "nodes": 1}]}, {"time": 1737559800, "users": [{"name": "gloomyred82", "nodes": 1}, {"name": "simplefrog47", "nodes": 1}, {"name": "impulsecanopener30", "nodes": 2}]}, {"time": 1737545400, "users": [{"name": "gloomyred82", "nodes": 1}, {"name": "simplefrog47", "nodes": 1}, {"name": "impulsecanopener30", "nodes": 2}]}, {"time": 1737546000, "users": [{"name": "simplefrog47", "nodes": 1}, {"name": "gloomyred82", "nodes": 1}, {"name": "impulsecanopener30", "nodes": 2}]}, {"time": 1737558900, "users": [{"name": "simplefrog47", "nodes": 1}, {"name": "gloomyred82", "nodes": 1}, {"name": "impulsecanopener30", "nodes": 2}]}, {"time": 1737543000, "users": [{"name": "impulsecanopener30", "nodes": 2}, {"name": "simplefrog47", "nodes": 1}, {"name": "gloomyred82", "nodes": 1}]}, {"time": 1737552000, "users": [{"name": "impulsecanopener30", "nodes": 2}, {"name": "simplefrog47", "nodes": 1}, {"name": "gloomyred82", "nodes": 1}]}, {"time": 1737541200, "users": [{"name": "impulsecanopener30", "nodes": 2}, {"name": "simplefrog47", "nodes": 1}, {"name": "gloomyred82", "nodes": 1}]}, {"time": 1737549900, "users": [{"name": "gloomyred82", "nodes": 1}, {"name": "impulsecanopener30", "nodes": 2}, {"name": "simplefrog47", "nodes": 1}]}, {"time": 1737560400, "users": [{"name": "simplefrog47", "nodes": 1}, {"name": "gloomyred82", "nodes": 1}, {"name": "impulsecanopener30", "nodes": 2}]}, {"time": 1737541500, "users": [{"name": "impulsecanopener30", "nodes": 2}, {"name": "simplefrog47", "nodes": 1}, {"name": "gloomyred82", "nodes": 1}]}, {"time": 1737552300, "users": [{"name": "simplefrog47", "nodes": 1}, {"name": "gloomyred82", "nodes": 1}, {"name": "impulsecanopener30", "nodes": 2}]}, {"time": 1737540600, "users": [{"name": "gloomyred82", "nodes": 1}, {"name": "simplefrog47", "nodes": 1}, {"name": "impulsecanopener30", "nodes": 2}]}, {"time": 1737541800, "users": [{"name": "simplefrog47", "nodes": 1}, {"name": "gloomyred82", "nodes": 1}, {"name": "impulsecanopener30", "nodes": 2}]}, {"time": 1737543900, "users": [{"name": "simplefrog47", "nodes": 1}, {"name": "gloomyred82", "nodes": 1}, {"name": "impulsecanopener30", "nodes": 2}]}, {"time": 1737543600, "users": [{"name": "impulsecanopener30", "nodes": 2}, {"name": "simplefrog47", "nodes": 1}, {"name": "gloomyred82", "nodes": 1}]}, {"time": 1737557100, "users": [{"name": "gloomyred82", "nodes": 1}, {"name": "simplefrog47", "nodes": 1}, {"name": "impulsecanopener30", "nodes": 2}]}, {"time": 1737559500, "users": [{"name": "impulsecanopener30", "nodes": 2}, {"name": "simplefrog47", "nodes": 1}, {"name": "gloomyred82", "nodes": 1}]}, {"time": 1737556500, "users": [{"name": "gloomyred82", "nodes": 1}, {"name": "simplefrog47", "nodes": 1}, {"name": "impulsecanopener30", "nodes": 2}]}, {"time": 1737560700, "users": [{"name": "simplefrog47", "nodes": 1}, {"name": "impulsecanopener30", "nodes": 2}, {"name": "gloomyred82", "nodes": 1}]}, {"time": 1737555300, "users": [{"name": "impulsecanopener30", "nodes": 2}, {"name": "simplefrog47", "nodes": 1}, {"name": "gloomyred82", "nodes": 1}]}, {"time": 1737544200, "users": [{"name": "impulsecanopener30", "nodes": 2}, {"name": "gloomyred82", "nodes": 1}, {"name": "simplefrog47", "nodes": 1}]}, {"time": 1737558300, "users": [{"name": "gloomyred82", "nodes": 1}, {"name": "impulsecanopener30", "nodes": 2}, {"name": "simplefrog47", "nodes": 1}]}, {"time": 1737549600, "users": [{"name": "gloomyred82", "nodes": 1}, {"name": "simplefrog47", "nodes": 1}, {"name": "impulsecanopener30", "nodes": 2}]}, {"time": 1737561300, "users": [{"name": "gloomyred82", "nodes": 1}, {"name": "simplefrog47", "nodes": 1}, {"name": "impulsecanopener30", "nodes": 2}]}, {"time": 1737556800, "users": [{"name": "impulsecanopener30", "nodes": 2}, {"name": "simplefrog47", "nodes": 1}, {"name": "gloomyred82", "nodes": 1}]}, {"time": 1737559200, "users": [{"name": "impulsecanopener30", "nodes": 2}, {"name": "gloomyred82", "nodes": 1}, {"name": "simplefrog47", "nodes": 1}]}, {"time": 1737542400, "users": [{"name": "impulsecanopener30", "nodes": 2}, {"name": "gloomyred82", "nodes": 1}, {"name": "simplefrog47", "nodes": 1}]}, {"time": 1737545100, "users": [{"name": "impulsecanopener30", "nodes": 2}, {"name": "simplefrog47", "nodes": 1}, {"name": "gloomyred82", "nodes": 1}]}, {"time": 1737546600, "users": [{"name": "impulsecanopener30", "nodes": 2}, {"name": "gloomyred82", "nodes": 1}, {"name": "simplefrog47", "nodes": 1}]}, {"time": 1737551100, "users": [{"name": "gloomyred82", "nodes": 1}, {"name": "impulsecanopener30", "nodes": 2}, {"name": "simplefrog47", "nodes": 1}]}, {"time": 1737548400, "users": [{"name": "gloomyred82", "nodes": 1}, {"name": "impulsecanopener30", "nodes": 2}, {"name": "simplefrog47", "nodes": 1}]}, {"time": 1737551400, "users": [{"name": "impulsecanopener30", "nodes": 2}, {"name": "gloomyred82", "nodes": 1}, {"name": "simplefrog47", "nodes": 1}]}, {"time": 1737540900, "users": [{"name": "gloomyred82", "nodes": 1}, {"name": "simplefrog47", "nodes": 1}, {"name": "impulsecanopener30", "nodes": 2}]}]