[{"time": 1736686800, "users": [{"name": "spinalflakily41", "nodes": 1}, {"name": "sharesubsidy79", "nodes": 1}, {"name": "wisechampion33", "nodes": 1}, {"name": "neverunpaid84", "nodes": 1}, {"name": "simplefrog47", "nodes": 3}, {"name": "septicthicket02", "nodes": 1}, {"name": "lazycoyote28", "nodes": 4}, {"name": "diligencesuspense91", "nodes": 1}, {"name": "strikingbear55", "nodes": 1}, {"name": "trophytiara85", "nodes": 1}, {"name": "savvyant41", "nodes": 1}, {"name": "handworksmooth06", "nodes": 1}, {"name": "beyondboulder34", "nodes": 1}, {"name": "impulsecanopener30", "nodes": 2}, {"name": "papercolony51", "nodes": 1}]}, {"time": 1736704800, "users": [{"name": "handworksmooth06", "nodes": 1}, {"name": "lazycoyote28", "nodes": 4}, {"name": "neverunpaid84", "nodes": 1}, {"name": "beyondboulder34", "nodes": 1}, {"name": "trophytiara85", "nodes": 1}, {"name": "wisechampion33", "nodes": 1}, {"name": "savvyant41", "nodes": 1}, {"name": "septicthicket02", "nodes": 1}, {"name": "papercolony51", "nodes": 1}, {"name": "spinalflakily41", "nodes": 1}, {"name": "strikingbear55", "nodes": 1}, {"name": "sharesubsidy79", "nodes": 1}, {"name": "impulsecanopener30", "nodes": 2}, {"name": "diligencesuspense91", "nodes": 1}, {"name": "simplefrog47", "nodes": 3}]}, {"time": 1736719200, "users": [{"name": "lazycoyote28", "nodes": 4}, {"name": "savvyant41", "nodes": 1}, {"name": "beyondboulder34", "nodes": 1}, {"name": "spinalflakily41", "nodes": 1}, {"name": "diligencesuspense91", "nodes": 1}, {"name": "septicthicket02", "nodes": 1}, {"name": "trophytiara85", "nodes": 1}, {"name": "wisechampion33", "nodes": 1}, {"name": "impulsecanopener30", "nodes": 2}, {"name": "strikingbear55", "nodes": 1}, {"name": "sharesubsidy79", "nodes": 1}, {"name": "simplefrog47", "nodes": 3}, {"name": "neverunpaid84", "nodes": 1}, {"name": "handworksmooth06", "nodes": 1}, {"name": "papercolony51", "nodes": 1}]}, {"time": 1736650800, "users": [{"name": "wisechampion33", "nodes": 1}, {"name": "beyondboulder34", "nodes": 1}, {"name": "spinalflakily41", "nodes": 1}, {"name": "trophytiara85", "nodes": 1}, {"name": "sharesubsidy79", "nodes": 1}, {"name": "impulsecanopener30", "nodes": 2}, {"name": "savvyant41", "nodes": 1}, {"name": "papercolony51", "nodes": 1}, {"name": "septicthicket02", "nodes": 1}, {"name": "strikingbear55", "nodes": 1}, {"name": "lazycoyote28", "nodes": 4}, {"name": "simplefrog47", "nodes": 3}, {"name": "diligencesuspense91", "nodes": 1}, {"name": "handworksmooth06", "nodes": 1}, {"name": "neverunpaid84", "nodes": 1}]}, {"time": 1736715600, "users": [{"name": "impulsecanopener30", "nodes": 2}, {"name": "lazycoyote28", "nodes": 4}, {"name": "spinalflakily41", "nodes": 1}, {"name": "simplefrog47", "nodes": 3}, {"name": "beyondboulder34", "nodes": 1}, {"name": "sharesubsidy79", "nodes": 1}, {"name": "neverunpaid84", "nodes": 1}, {"name": "wisechampion33", "nodes": 1}, {"name": "savvyant41", "nodes": 1}, {"name": "trophytiara85", "nodes": 1}, {"name": "handworksmooth06", "nodes": 1}, {"name": "septicthicket02", "nodes": 1}, {"name": "papercolony51", "nodes": 1}, {"name": "strikingbear55", "nodes": 1}, {"name": "diligencesuspense91", "nodes": 1}]}, {"time": 1736654400, "users": [{"name": "spinalflakily41", "nodes": 1}, {"name": "impulsecanopener30", "nodes": 2}, {"name": "handworksmooth06", "nodes": 1}, {"name": "trophytiara85", "nodes": 1}, {"name": "simplefrog47", "nodes": 3}, {"name": "diligencesuspense91", "nodes": 1}, {"name": "neverunpaid84", "nodes": 1}, {"name": "lazycoyote28", "nodes": 4}, {"name": "septicthicket02", "nodes": 1}, {"name": "strikingbear55", "nodes": 1}, {"name": "papercolony51", "nodes": 1}, {"name": "sharesubsidy79", "nodes": 1}, {"name": "wisechampion33", "nodes": 1}, {"name": "savvyant41", "nodes": 1}, {"name": "beyondboulder34", "nodes": 1}]}, {"time": 1736722800, "users": [{"name": "savvyant41", "nodes": 1}, {"name": "septicthicket02", "nodes": 1}, {"name": "diligencesuspense91", "nodes": 1}, {"name": "lazycoyote28", "nodes": 4}, {"name": "trophytiara85", "nodes": 1}, {"name": "simplefrog47", "nodes": 3}, {"name": "sharesubsidy79", "nodes": 1}, {"name": "neverunpaid84", "nodes": 1}, {"name": "papercolony51", "nodes": 1}, {"name": "wisechampion33", "nodes": 1}, {"name": "handworksmooth06", "nodes": 1}, {"name": "strikingbear55", "nodes": 1}, {"name": "impulsecanopener30", "nodes": 2}, {"name": "spinalflakily41", "nodes": 1}, {"name": "beyondboulder34", "nodes": 1}]}, {"time": 1736730000, "users": [{"name": "septicthicket02", "nodes": 1}, {"name": "wisechampion33", "nodes": 1}, {"name": "impulsecanopener30", "nodes": 2}, {"name": "spinalflakily41", "nodes": 1}, {"name": "handworksmooth06", "nodes": 1}, {"name": "diligencesuspense91", "nodes": 1}, {"name": "papercolony51", "nodes": 1}, {"name": "beyondboulder34", "nodes": 1}, {"name": "savvyant41", "nodes": 1}, {"name": "lazycoyote28", "nodes": 4}, {"name": "sharesubsidy79", "nodes": 1}, {"name": "simplefrog47", "nodes": 3}, {"name": "strikingbear55", "nodes": 1}, {"name": "trophytiara85", "nodes": 1}, {"name": "neverunpaid84", "nodes": 1}]}, {"time": 1736733600, "users": [{"name": "trophytiara85", "nodes": 1}, {"name": "septicthicket02", "nodes": 1}, {"name": "simplefrog47", "nodes": 3}, {"name": "handworksmooth06", "nodes": 1}, {"name": "wisechampion33", "nodes": 1}, {"name": "sharesubsidy79", "nodes": 1}, {"name": "neverunpaid84", "nodes": 1}, {"name": "lazycoyote28", "nodes": 4}, {"name": "spinalflakily41", "nodes": 1}, {"name": "strikingbear55", "nodes": 1}, {"name": "impulsecanopener30", "nodes": 2}, {"name": "diligencesuspense91", "nodes": 1}, {"name": "papercolony51", "nodes": 1}, {"name": "savvyant41", "nodes": 1}, {"name": "beyondboulder34", "nodes": 1}]}, {"time": 1736661600, "users": [{"name": "wisechampion33", "nodes": 1}, {"name": "beyondboulder34", "nodes": 1}, {"name": "strikingbear55", "nodes": 1}, {"name": "spinalflakily41", "nodes": 1}, {"name": "papercolony51", "nodes": 1}, {"name": "impulsecanopener30", "nodes": 2}, {"name": "lazycoyote28", "nodes": 4}, {"name": "septicthicket02", "nodes": 1}, {"name": "simplefrog47", "nodes": 3}, {"name": "neverunpaid84", "nodes": 1}, {"name": "trophytiara85", "nodes": 1}, {"name": "diligencesuspense91", "nodes": 1}, {"name": "sharesubsidy79", "nodes": 1}, {"name": "savvyant41", "nodes": 1}, {"name": "handworksmooth06", "nodes": 1}]}, {"time": 1736694000, "users": [{"name": "sharesubsidy79", "nodes": 1}, {"name": "simplefrog47", "nodes": 3}, {"name": "septicthicket02", "nodes": 1}, {"name": "lazycoyote28", "nodes": 4}, {"name": "papercolony51", "nodes": 1}, {"name": "beyondboulder34", "nodes": 1}, {"name": "strikingbear55", "nodes": 1}, {"name": "impulsecanopener30", "nodes": 2}, {"name": "neverunpaid84", "nodes": 1}, {"name": "wisechampion33", "nodes": 1}, {"name": "handworksmooth06", "nodes": 1}, {"name": "trophytiara85", "nodes": 1}, {"name": "savvyant41", "nodes": 1}, {"name": "diligencesuspense91", "nodes": 1}, {"name": "spinalflakily41", "nodes": 1}]}, {"time": 1736708400, "users": [{"name": "neverunpaid84", "nodes": 1}, {"name": "impulsecanopener30", "nodes": 2}, {"name": "strikingbear55", "nodes": 1}, {"name": "lazycoyote28", "nodes": 4}, {"name": "sharesubsidy79", "nodes": 1}, {"name": "savvyant41", "nodes": 1}, {"name": "simplefrog47", "nodes": 3}, {"name": "septicthicket02", "nodes": 1}, {"name": "papercolony51", "nodes": 1}, {"name": "beyondboulder34", "nodes": 1}, {"name": "diligencesuspense91", "nodes": 1}, {"name": "wisechampion33", "nodes": 1}, {"name": "trophytiara85", "nodes": 1}, {"name": "handworksmooth06", "nodes": 1}, {"name": "spinalflakily41", "nodes": 1}]}, {"time": 1736658000, "users": [{"name": "lazycoyote28", "nodes": 4}, {"name": "septicthicket02", "nodes": 1}, {"name": "diligencesuspense91", "nodes": 1}, {"name": "simplefrog47", "nodes": 3}, {"name": "papercolony51", "nodes": 1}, {"name": "beyondboulder34", "nodes": 1}, {"name": "trophytiara85", "nodes": 1}, {"name": "sharesubsidy79", "nodes": 1}, {"name": "neverunpaid84", "nodes": 1}, {"name": "strikingbear55", "nodes": 1}, {"name": "handworksmooth06", "nodes": 1}, {"name": "savvyant41", "nodes": 1}, {"name": "spinalflakily41", "nodes": 1}, {"name": "impulsecanopener30", "nodes": 2}, {"name": "wisechampion33", "nodes": 1}]}, {"time": 1736676000, "users": [{"name": "spinalflakily41", "nodes": 1}, {"name": "beyondboulder34", "nodes": 1}, {"name": "trophytiara85", "nodes": 1}, {"name": "savvyant41", "nodes": 1}, {"name": "impulsecanopener30", "nodes": 2}, {"name": "lazycoyote28", "nodes": 4}, {"name": "sharesubsidy79", "nodes": 1}, {"name": "simplefrog47", "nodes": 3}, {"name": "handworksmooth06", "nodes": 1}, {"name": "septicthicket02", "nodes": 1}, {"name": "neverunpaid84", "nodes": 1}, {"name": "papercolony51", "nodes": 1}, {"name": "diligencesuspense91", "nodes": 1}, {"name": "strikingbear55", "nodes": 1}, {"name": "wisechampion33", "nodes": 1}]}, {"time": 1736690400, "users": [{"name": "trophytiara85", "nodes": 1}, {"name": "lazycoyote28", "nodes": 4}, {"name": "neverunpaid84", "nodes": 1}, {"name": "diligencesuspense91", "nodes": 1}, {"name": "beyondboulder34", "nodes": 1}, {"name": "handworksmooth06", "nodes": 1}, {"name": "savvyant41", "nodes": 1}, {"name": "spinalflakily41", "nodes": 1}, {"name": "wisechampion33", "nodes": 1}, {"name": "septicthicket02", "nodes": 1}, {"name": "simplefrog47", "nodes": 3}, {"name": "papercolony51", "nodes": 1}, {"name": "sharesubsidy79", "nodes": 1}, {"name": "impulsecanopener30", "nodes": 2}, {"name": "strikingbear55", "nodes": 1}]}, {"time": 1736737200, "users": [{"name": "lazycoyote28", "nodes": 4}, {"name": "wisechampion33", "nodes": 1}, {"name": "handworksmooth06", "nodes": 1}, {"name": "sharesubsidy79", "nodes": 1}, {"name": "septicthicket02", "nodes": 1}, {"name": "neverunpaid84", "nodes": 1}, {"name": "spinalflakily41", "nodes": 1}, {"name": "beyondboulder34", "nodes": 1}, {"name": "impulsecanopener30", "nodes": 2}, {"name": "savvyant41", "nodes": 1}, {"name": "strikingbear55", "nodes": 1}, {"name": "simplefrog47", "nodes": 3}, {"name": "diligencesuspense91", "nodes": 1}, {"name": "trophytiara85", "nodes": 1}, {"name": "papercolony51", "nodes": 1}]}, {"time": 1736712000, "users": [{"name": "diligencesuspense91", "nodes": 1}, {"name": "handworksmooth06", "nodes": 1}, {"name": "beyondboulder34", "nodes": 1}, {"name": "trophytiara85", "nodes": 1}, {"name": "septicthicket02", "nodes": 1}, {"name": "lazycoyote28", "nodes": 4}, {"name": "strikingbear55", "nodes": 1}, {"name": "papercolony51", "nodes": 1}, {"name": "savvyant41", "nodes": 1}, {"name": "simplefrog47", "nodes": 3}, {"name": "sharesubsidy79", "nodes": 1}, {"name": "spinalflakily41", "nodes": 1}, {"name": "impulsecanopener30", "nodes": 2}, {"name": "neverunpaid84", "nodes": 1}, {"name": "wisechampion33", "nodes": 1}]}, {"time": 1736683200, "users": [{"name": "beyondboulder34", "nodes": 1}, {"name": "septicthicket02", "nodes": 1}, {"name": "papercolony51", "nodes": 1}, {"name": "savvyant41", "nodes": 1}, {"name": "impulsecanopener30", "nodes": 2}, {"name": "wisechampion33", "nodes": 1}, {"name": "lazycoyote28", "nodes": 4}, {"name": "strikingbear55", "nodes": 1}, {"name": "handworksmooth06", "nodes": 1}, {"name": "sharesubsidy79", "nodes": 1}, {"name": "diligencesuspense91", "nodes": 1}, {"name": "trophytiara85", "nodes": 1}, {"name": "spinalflakily41", "nodes": 1}, {"name": "simplefrog47", "nodes": 3}, {"name": "neverunpaid84", "nodes": 1}]}, {"time": 1736697600, "users": [{"name": "handworksmooth06", "nodes": 1}, {"name": "diligencesuspense91", "nodes": 1}, {"name": "sharesubsidy79", "nodes": 1}, {"name": "spinalflakily41", "nodes": 1}, {"name": "wisechampion33", "nodes": 1}, {"name": "septicthicket02", "nodes": 1}, {"name": "simplefrog47", "nodes": 3}, {"name": "papercolony51", "nodes": 1}, {"name": "lazycoyote28", "nodes": 4}, {"name": "impulsecanopener30", "nodes": 2}, {"name": "trophytiara85", "nodes": 1}, {"name": "neverunpaid84", "nodes": 1}, {"name": "savvyant41", "nodes": 1}, {"name": "beyondboulder34", "nodes": 1}, {"name": "strikingbear55", "nodes": 1}]}, {"time": 1736665200, "users": [{"name": "savvyant41", "nodes": 1}, {"name": "trophytiara85", "nodes": 1}, {"name": "wisechampion33", "nodes": 1}, {"name": "handworksmooth06", "nodes": 1}, {"name": "papercolony51", "nodes": 1}, {"name": "septicthicket02", "nodes": 1}, {"name": "neverunpaid84", "nodes": 1}, {"name": "strikingbear55", "nodes": 1}, {"name": "spinalflakily41", "nodes": 1}, {"name": "lazycoyote28", "nodes": 4}, {"name": "diligencesuspense91", "nodes": 1}, {"name": "simplefrog47", "nodes": 3}, {"name": "sharesubsidy79", "nodes": 1}, {"name": "impulsecanopener30", "nodes": 2}, {"name": "beyondboulder34", "nodes": 1}]}, {"time": 1736668800, "users": [{"name": "wisechampion33", "nodes": 1}, {"name": "spinalflakily41", "nodes": 1}, {"name": "trophytiara85", "nodes": 1}, {"name": "strikingbear55", "nodes": 1}, {"name": "diligencesuspense91", "nodes": 1}, {"name": "simplefrog47", "nodes": 3}, {"name": "septicthicket02", "nodes": 1}, {"name": "savvyant41", "nodes": 1}, {"name": "lazycoyote28", "nodes": 4}, {"name": "beyondboulder34", "nodes": 1}, {"name": "neverunpaid84", "nodes": 1}, {"name": "impulsecanopener30", "nodes": 2}, {"name": "papercolony51", "nodes": 1}, {"name": "sharesubsidy79", "nodes": 1}, {"name": "handworksmooth06", "nodes": 1}]}, {"time": 1736726400, "users": [{"name": "trophytiara85", "nodes": 1}, {"name": "impulsecanopener30", "nodes": 2}, {"name": "beyondboulder34", "nodes": 1}, {"name": "simplefrog47", "nodes": 3}, {"name": "septicthicket02", "nodes": 1}, {"name": "papercolony51", "nodes": 1}, {"name": "lazycoyote28", "nodes": 4}, {"name": "spinalflakily41", "nodes": 1}, {"name": "strikingbear55", "nodes": 1}, {"name": "sharesubsidy79", "nodes": 1}, {"name": "handworksmooth06", "nodes": 1}, {"name": "savvyant41", "nodes": 1}, {"name": "neverunpaid84", "nodes": 1}, {"name": "wisechampion33", "nodes": 1}, {"name": "diligencesuspense91", "nodes": 1}]}, {"time": 1736672400, "users": [{"name": "lazycoyote28", "nodes": 4}, {"name": "wisechampion33", "nodes": 1}, {"name": "diligencesuspense91", "nodes": 1}, {"name": "septicthicket02", "nodes": 1}, {"name": "strikingbear55", "nodes": 1}, {"name": "sharesubsidy79", "nodes": 1}, {"name": "neverunpaid84", "nodes": 1}, {"name": "handworksmooth06", "nodes": 1}, {"name": "spinalflakily41", "nodes": 1}, {"name": "simplefrog47", "nodes": 3}, {"name": "trophytiara85", "nodes": 1}, {"name": "savvyant41", "nodes": 1}, {"name": "impulsecanopener30", "nodes": 2}, {"name": "papercolony51", "nodes": 1}, {"name": "beyondboulder34", "nodes": 1}]}, {"time": 1736701200, "users": [{"name": "septicthicket02", "nodes": 1}, {"name": "wisechampion33", "nodes": 1}, {"name": "papercolony51", "nodes": 1}, {"name": "diligencesuspense91", "nodes": 1}, {"name": "simplefrog47", "nodes": 3}, {"name": "neverunpaid84", "nodes": 1}, {"name": "lazycoyote28", "nodes": 4}, {"name": "trophytiara85", "nodes": 1}, {"name": "sharesubsidy79", "nodes": 1}, {"name": "strikingbear55", "nodes": 1}, {"name": "spinalflakily41", "nodes": 1}, {"name": "impulsecanopener30", "nodes": 2}, {"name": "beyondboulder34", "nodes": 1}, {"name": "handworksmooth06", "nodes": 1}, {"name": "savvyant41", "nodes": 1}]}, {"time": 1736679600, "users": [{"name": "sharesubsidy79", "nodes": 1}, {"name": "septicthicket02", "nodes": 1}, {"name": "strikingbear55", "nodes": 1}, {"name": "beyondboulder34", "nodes": 1}, {"name": "spinalflakily41", "nodes": 1}, {"name": "simplefrog47", "nodes": 3}, {"name": "wisechampion33", "nodes": 1}, {"name": "handworksmooth06", "nodes": 1}, {"name": "savvyant41", "nodes": 1}, {"name": "diligencesuspense91", "nodes": 1}, {"name": "neverunpaid84", "nodes": 1}, {"name": "lazycoyote28", "nodes": 4}, {"name": "papercolony51", "nodes": 1}, {"name": "trophytiara85", "nodes": 1}, {"name": "impulsecanopener30", "nodes": 2}]}]